path.py
setup.py
forked_path.egg-info/PKG-INFO
forked_path.egg-info/SOURCES.txt
forked_path.egg-info/dependency_links.txt
forked_path.egg-info/not-zip-safe
forked_path.egg-info/top_level.txt