Metadata-Version: 1.0
Name: forked-path
Version: 0.1
Summary: An object oriented file path module
Home-page: http://github.com/Singletoned/forked-path
Author: Ed Singleton
Author-email: singletoned@gmail.com
License: UNKNOWN
Keywords: path path.py file
Platform: UNKNOWN
Classifier: Programming Language :: Python
Classifier: License :: Freely Distributable
Classifier: Operating System :: OS Independent
Classifier: Intended Audience :: Developers
Classifier: Topic :: Software Development :: Libraries :: Python Modules
